aio/__init__.py
aio/aio_theme_changer.py
aio/aio_theme_switch.py
dash_bootstrap_templates/__init__.py
dash_bootstrap_templates/templates/bootstrap.json
dash_bootstrap_templates/templates/bootstrap_dark.json
dash_bootstrap_templates/templates/cerulean.json
dash_bootstrap_templates/templates/cerulean_dark.json
dash_bootstrap_templates/templates/cosmo.json
dash_bootstrap_templates/templates/cosmo_dark.json
dash_bootstrap_templates/templates/cyborg.json
dash_bootstrap_templates/templates/cyborg_dark.json
dash_bootstrap_templates/templates/darkly.json
dash_bootstrap_templates/templates/darkly_dark.json
dash_bootstrap_templates/templates/flatly.json
dash_bootstrap_templates/templates/flatly_dark.json
dash_bootstrap_templates/templates/journal.json
dash_bootstrap_templates/templates/journal_dark.json
dash_bootstrap_templates/templates/litera.json
dash_bootstrap_templates/templates/litera_dark.json
dash_bootstrap_templates/templates/lumen.json
dash_bootstrap_templates/templates/lumen_dark.json
dash_bootstrap_templates/templates/lux.json
dash_bootstrap_templates/templates/lux_dark.json
dash_bootstrap_templates/templates/materia.json
dash_bootstrap_templates/templates/materia_dark.json
dash_bootstrap_templates/templates/minty.json
dash_bootstrap_templates/templates/minty_dark.json
dash_bootstrap_templates/templates/morph.json
dash_bootstrap_templates/templates/morph_dark.json
dash_bootstrap_templates/templates/pulse.json
dash_bootstrap_templates/templates/pulse_dark.json
dash_bootstrap_templates/templates/quartz.json
dash_bootstrap_templates/templates/quartz_dark.json
dash_bootstrap_templates/templates/sandstone.json
dash_bootstrap_templates/templates/sandstone_dark.json
dash_bootstrap_templates/templates/simplex.json
dash_bootstrap_templates/templates/simplex_dark.json
dash_bootstrap_templates/templates/sketchy.json
dash_bootstrap_templates/templates/sketchy_dark.json
dash_bootstrap_templates/templates/slate.json
dash_bootstrap_templates/templates/slate_dark.json
dash_bootstrap_templates-2.0.0.dist-info/LICENSE
dash_bootstrap_templates-2.0.0.dist-info/METADATA
dash_bootstrap_templates-2.0.0.dist-info/WHEEL
dash_bootstrap_templates-2.0.0.dist-info/top_level.txt
dash_bootstrap_templates-2.0.0.dist-info/RECORD
