Metadata-Version: 2.2
Name: dash-bootstrap-templates
Version: 2.0.0
Summary: A collection of Plotly figure templates with a Bootstrap theme
Home-page: https://github.com/AnnMarieW/dash-bootstrap-templates
Author: AnnMarieW
License: MIT
Classifier: Development Status :: 3 - Alpha
Classifier: Framework :: Dash
Classifier: License :: OSI Approved :: MIT License
Classifier: Programming Language :: Python :: 3.7
Classifier: Programming Language :: Python :: 3.8
Classifier: Programming Language :: Python :: 3.9
Classifier: Programming Language :: Python :: 3.10
Classifier: Programming Language :: Python :: 3.11
Classifier: Programming Language :: Python :: 3 :: Only
Classifier: Topic :: Scientific/Engineering :: Visualization
License-File: LICENSE
Requires-Dist: dash
Requires-Dist: dash-bootstrap-components>=1.0.0
Requires-Dist: importlib_metadata>=3.4.0; python_version == "3.7"
Requires-Dist: importlib_resources>=5.1.0; python_version < "3.9"
Requires-Dist: numpy
Requires-Dist: plotly<7,>=6
Provides-Extra: dev
Requires-Dist: tinycss2; extra == "dev"
Requires-Dist: spectra; extra == "dev"
